aiohttp_ntlm/__init__.py
aiohttp_ntlm/base.py
aiohttp_ntlm-0.1.4.dist-info/METADATA
aiohttp_ntlm-0.1.4.dist-info/WHEEL
aiohttp_ntlm-0.1.4.dist-info/RECORD
