Metadata-Version: 2.3
Name: aiohttp-ntlm
Version: 0.1.4
Summary: NTLM authentication middleware for aiohttp
License: MIT
Author: lowkeymodestme@gmail.com
Requires-Python: >=3.11
Classifier: License :: OSI Approved :: MIT License
Classifier: Programming Language :: Python :: 3
Classifier: Programming Language :: Python :: 3.11
Classifier: Programming Language :: Python :: 3.12
Classifier: Programming Language :: Python :: 3.13
Requires-Dist: aiohttp (>=3.12.0,<4.0.0)
Requires-Dist: pyspnego (>=0.11.0,<0.12.0)
